DESCRIPTION.rst
MANIFEST.in
README.md
setup.cfg
setup.py
./pyhsm/convert.py
./pyhsm/eccurveoids.py
./pyhsm/eccurves.py
./pyhsm/hsmclient.py
./pyhsm/hsmenums.py
./pyhsm/hsmerror.py
./pyhsm/hsmmechinfo.py
./pyhsm/hsmobject.py
./pyhsm/hsmslot.py
py_hsm.egg-info/PKG-INFO
py_hsm.egg-info/SOURCES.txt
py_hsm.egg-info/dependency_links.txt
py_hsm.egg-info/top_level.txt
pyhsm/__init__.py
pyhsm/convert.py
pyhsm/eccurveoids.py
pyhsm/eccurves.py
pyhsm/hsmclient.py
pyhsm/hsmenums.py
pyhsm/hsmerror.py
pyhsm/hsmmechinfo.py
pyhsm/hsmobject.py
pyhsm/hsmslot.py
tests/__init__.py
tests/unit_tests/__init__.py
tests/unit_tests/unit_tests.py